{
    "nodes":[
      {"name":"InsertHandler::HandleEvent","id":0},
      {"name":"Event::id","id":1},
      {"name":"Event::context","id":2},
      {"name":"DataReader::DataReader","id":3},
      {"name":"DataReader::ReadString","id":4},
      {"name":"DatasetManager::GetInstance","id":5},
      {"name":"DatasetManager::AddDataset","id":6},
      {"name":"RowChunk::RowChunk","id":7},
      {"name":"DataReader::ReadInt","id":8},
      {"name":"DatasetManager::AddField","id":9},
      {"name":"Dataset::name","id":10},
      {"name":"RowChunk::set_buffer","id":11},
      {"name":"DataReader::ReadInt","id":12},
      {"name":"DataReader::SkipData","id":13},
      {"name":"RowChunk::set_size","id":14},
      {"name":"RowChunk::size","id":15},

      {"name":"DataReader::ReadString","id":16},
      {"name":"get_file_size","id":17},

      {"name":"RowChunk::set_size","id":18},
      {"name":"RowChunk::size","id":19},
      {"name":"UnitManager::GetInstance","id":20},
      {"name":"UnitManager::AddRowChunk","id":21},

      {"name":"DataReader::ReadInt","id":22},
      {"name":"RowChunk::set_size","id":23},
      {"name":"RowChunk::size","id":24},
      {"name":"UnitManager::GetInstance","id":25},
      {"name":"UnitManager::AddRowChunk","id":26},

      {"name":"UnitWriter::fixed","id":27},
      {"name":"InsertTask::InsertTask","id":28},
      {"name":"Dataset::AddTask","id":29},
      {"name":"InsertTask::set_unit_id","id":30},
      {"name":"Dataset::GetUnitId","id":31},
      {"name":"Event::set_id","id":32},
      {"name":"Task::PushEvent","id":33},
      {"name":"EventManager::GetInstance","id":34},
      {"name":"EventManager::Post","id":35},


      {"name":"Logger::Logger","id":36},
      {"name":"Event::context","id":37},
      {"name":"DataReader::ReadString","id":38},
      {"name":"DatasetManager::GetInstance","id":39},
      {"name":"DatasetManager::GetDataset","id":40},
      {"name":"FlushResponseTask::FlushResponseTask","id":41},

      {"name":"Dataset::get_tasks","id":42},
      {"name":"Task::set_next_task","id":43},
      {"name":"UnitManager::GetInstance","id":44},
      {"name":"UnitManager::FixUnitWriter","id":45},

      {"name":"UnitWriter::num_chunks","id":46},
      {"name":"InsertTask::InsertTask","id":47},
      {"name":"Dataset::AddTask","id":48},
      {"name":"InsertTask::set_unit_id","id":49},
      {"name":"Dataset::GetUnitId","id":50},
      {"name":"Task::set_next_task","id":51},
      {"name":"Event::set_id","id":52},
      {"name":"Task::PushEvent","id":53},
      {"name":"EventManager::GetInstance","id":54},
      {"name":"EventManager::Post","id":55},

      {"name":"Task::get_num_deps_tasks","id":56},
      {"name":"FlushResponseTask::Execute","id":57},

      {"name":"END","id":58},
      {"name":"IF","id":59},
      {"name":"IF","id":60},
      {"name":"IF","id":61},
      {"name":"IF","id":62},
      {"name":"IF","id":63},
      {"name":"IF","id":64},
      {"name":"START","id":65},
      {"name":"IF","id":66}



    ],
    "links":[
      {"source":65,"target":0},
      {"source":0,"target":1},
      {"source":1,"target":59},

      {"source":59,"target":2},
      {"source":2,"target":3},
      {"source":3,"target":4},
      {"source":4,"target":5},
      {"source":5,"target":6},
      {"source":6,"target":7},
      {"source":7,"target":8},
      {"source":8,"target":9},
      {"source":9,"target":10},
      {"source":10,"target":11},
      {"source":11,"target":12},
      {"source":12,"target":13},
      {"source":13,"target":14},
      {"source":14,"target":15},
      {"source":15,"target":60},

      {"source":60,"target":16},
      {"source":16,"target":17},
      {"source":17,"target":64},

      {"source":64,"target":18},
      {"source":18,"target":19},
      {"source":19,"target":20},
      {"source":20,"target":21},
      {"source":21,"target":66},

      {"source":64,"target":66},

      {"source":60,"target":22},
      {"source":22,"target":23},
      {"source":23,"target":24},
      {"source":24,"target":25},
      {"source":25,"target":26},
      {"source":26,"target":66},

      {"source":66,"target":27},
      {"source":27,"target":28},
      {"source":28,"target":29},
      {"source":29,"target":30},
      {"source":30,"target":31},
      {"source":31,"target":32},
      {"source":32,"target":33},
      {"source":33,"target":34},
      {"source":34,"target":35},

      {"source":35,"target":58},
      {"source":66,"target":58},

      {"source":59,"target":36},
      {"source":36,"target":37},
      {"source":37,"target":38},
      {"source":38,"target":39},
      {"source":39,"target":40},
      {"source":40,"target":41},
      {"source":41,"target":62},

      {"source":62,"target":42},
      {"source":42,"target":43},
      {"source":43,"target":44},
      {"source":44,"target":45},
      {"source":45,"target":63},

      {"source":63,"target":46},
      {"source":46,"target":47},
      {"source":47,"target":48},
      {"source":48,"target":49},
      {"source":49,"target":50},
      {"source":50,"target":51},
      {"source":51,"target":52},
      {"source":52,"target":53},
      {"source":53,"target":54},
      {"source":54,"target":55},
      {"source":55,"target":61},
      {"source":62,"target":61},

      {"source":61,"target":58},
      {"source":61,"target":56},
      {"source":56,"target":57},
      {"source":57,"target":58}

    ],
	"groups":[
	  {"leaves":[2]}

	]
}
